Metadata-Version: 2.1
Name: example-pkg-xiangsheng
Version: 0.0.1
Summary: The first package of VOIX.
Home-page: https://github.com/pypa/sampleproject
Author: xiangsheng
Author-email: xiangsheng1325@sjtu.edu.cn
License: UNKNOWN
Platform: UNKNOWN
Classifier: Programming Language :: Python :: 3
Classifier: License :: OSI Approved :: MIT License
Classifier: Operating System :: OS Independent
